backend/Face_attend.py
backend/Face_sample_train.py
backend/__init__.py
backend/face_fetching.py
prastut_ai-1.0.0.dist-info/LICENSE
prastut_ai-1.0.0.dist-info/METADATA
prastut_ai-1.0.0.dist-info/WHEEL
prastut_ai-1.0.0.dist-info/entry_points.txt
prastut_ai-1.0.0.dist-info/top_level.txt
prastut_ai-1.0.0.dist-info/RECORD
