Metadata-Version: 2.2
Name: prastut-ai
Version: 1.0.0
Summary: A modern face recognition-based attendance system
Author-email: Prastut AI <adminprastutai@gmail.com>
License: MIT License
Project-URL: Homepage, https://github.com/yourusername/prastut-ai
Project-URL: Repository, https://github.com/yourusername/prastut-ai.git
Project-URL: Issues, https://github.com/yourusername/prastut-ai/issues
Keywords: face-recognition,attendance-system,deep-learning,education
Classifier: Development Status :: 4 - Beta
Classifier: Intended Audience :: Education
Classifier: Programming Language :: Python :: 3
Classifier: Programming Language :: Python :: 3.8
Classifier: Programming Language :: Python :: 3.9
Classifier: Programming Language :: Python :: 3.10
Classifier: Programming Language :: Python :: 3.11
Classifier: Programming Language :: Python :: 3.12
Classifier: License :: OSI Approved :: MIT License
Classifier: Operating System :: OS Independent
Classifier: Topic :: Education
Classifier: Topic :: Scientific/Engineering :: Artificial Intelligence
Classifier: Topic :: Scientific/Engineering :: Image Recognition
Requires-Python: >=3.8
License-File: LICENSE
Requires-Dist: Flask==2.3.3
Requires-Dist: Werkzeug==2.3.7
Requires-Dist: gunicorn==21.2.0
Requires-Dist: python-dotenv==1.0.0
Requires-Dist: numpy>=1.26.0
Requires-Dist: pandas>=2.1.0
Requires-Dist: requests==2.31.0
Requires-Dist: openpyxl==3.1.2
Requires-Dist: Pillow==10.0.0
Requires-Dist: opencv-python-headless>=4.9.0.80
Requires-Dist: imutils==0.5.4
Requires-Dist: facenet-pytorch==2.5.3
Requires-Dist: deepface==0.0.79
Requires-Dist: pinecone-client==2.2.4
Requires-Dist: firebase-admin==6.2.0
Provides-Extra: dev
Requires-Dist: pytest>=7.4.0; extra == "dev"
Requires-Dist: black>=23.0.0; extra == "dev"
Requires-Dist: flake8>=6.0.0; extra == "dev"
Requires-Dist: build; extra == "dev"
Requires-Dist: twine; extra == "dev"
